rebalance/__init__.py
portfolio_rebalance-0.1.0.dist-info/LICENSE
portfolio_rebalance-0.1.0.dist-info/METADATA
portfolio_rebalance-0.1.0.dist-info/WHEEL
portfolio_rebalance-0.1.0.dist-info/top_level.txt
portfolio_rebalance-0.1.0.dist-info/RECORD
