Metadata-Version: 2.1
Name: portfolio-rebalance
Version: 0.1.0
Summary: Discrete portfolio share allocation optimization.
Home-page: https://github.com/alienbrett/portfolio-rebalance
Author: Brett Graves
Author-email: alienbrett648@gmail.com
License: MIT
Platform: UNKNOWN
Classifier: License :: OSI Approved :: MIT License
Classifier: Programming Language :: Python
Classifier: Programming Language :: Python :: 3
Classifier: Programming Language :: Python :: 3.6
Classifier: Programming Language :: Python :: Implementation :: CPython
Classifier: Programming Language :: Python :: Implementation :: PyPy
Requires-Python: >=3.6.0
Requires-Dist: numpy
Requires-Dist: pandas
